odoo8_addon_account_bank_statement_import_fr_cfonb-8.0.0.1.0.99.dev17-py2.7-nspkg.pth
odoo8_addon_account_bank_statement_import_fr_cfonb-8.0.0.1.0.99.dev17.dist-info/METADATA
odoo8_addon_account_bank_statement_import_fr_cfonb-8.0.0.1.0.99.dev17.dist-info/RECORD
odoo8_addon_account_bank_statement_import_fr_cfonb-8.0.0.1.0.99.dev17.dist-info/WHEEL
odoo8_addon_account_bank_statement_import_fr_cfonb-8.0.0.1.0.99.dev17.dist-info/namespace_packages.txt
odoo8_addon_account_bank_statement_import_fr_cfonb-8.0.0.1.0.99.dev17.dist-info/top_level.txt
odoo_addons/account_bank_statement_import_fr_cfonb/README.rst
odoo_addons/account_bank_statement_import_fr_cfonb/__init__.py
odoo_addons/account_bank_statement_import_fr_cfonb/__openerp__.py
odoo_addons/account_bank_statement_import_fr_cfonb/account_bank_statement_import_fr_cfonb.py
odoo_addons/account_bank_statement_import_fr_cfonb/i18n/account_bank_statement_import_fr_cfonb.pot
odoo_addons/account_bank_statement_import_fr_cfonb/i18n/ca_ES.po
odoo_addons/account_bank_statement_import_fr_cfonb/i18n/fi.po
odoo_addons/account_bank_statement_import_fr_cfonb/i18n/fr.po
odoo_addons/account_bank_statement_import_fr_cfonb/i18n/nl_NL.po
odoo_addons/account_bank_statement_import_fr_cfonb/static/description/icon.png
